Workbook

Sheet Executive Summary
A1: FINANCIAL OPERATIONS AUDIT & RECONCILIATION DASHBOARD
A3: Automated 3-Way Reconciliation Model: Vendor Invoices vs. AP Ledger vs. Bank Disbursements | Project Portfolio
B5: TOTAL INVOICES AUDITED | D5: TOTAL BILLED VOLUME | F5: TOTAL RECONCILED | H5: TOTAL VARIANCE EXPOSURE
B6: =COUNTA('Reconciliation Engine'!A2:A41) | D6: =SUM('Reconciliation Engine'!C2:C41) | F6: =SUMIF('Reconciliation Engine'!H2:H41, "Fully Reconciled", 'Reconciliation Engine'!E2:E41) | H6: =SUM('Reconciliation Engine'!F2:F41)
B9: Audit Reconciliation Status Breakdown
B10: Reconciliation Status | C10: Count | D10: % of Total Volume | E10: Net Billed Exposure ($)
B11: Fully Reconciled | C11: =COUNTIF('Reconciliation Engine'!$H$2:$H$41, B11) | D11: =C11/$C$15 | E11: =SUMIF('Reconciliation Engine'!$H$2:$H$41, B11, 'Reconciliation Engine'!$C$2:$C$41)
B12: Missing in AP Ledger | C12: =COUNTIF('Reconciliation Engine'!$H$2:$H$41, B12) | D12: =C12/$C$15 | E12: =SUMIF('Reconciliation Engine'!$H$2:$H$41, B12, 'Reconciliation Engine'!$C$2:$C$41)
B13: Variance Detected | C13: =COUNTIF('Reconciliation Engine'!$H$2:$H$41, B13) | D13: =C13/$C$15 | E13: =SUMIF('Reconciliation Engine'!$H$2:$H$41, B13, 'Reconciliation Engine'!$C$2:$C$41)
B14: Pending Bank Disbursement | C14: =COUNTIF('Reconciliation Engine'!$H$2:$H$41, B14) | D14: =C14/$C$15 | E14: =SUMIF('Reconciliation Engine'!$H$2:$H$41, B14, 'Reconciliation Engine'!$C$2:$C$41)
B15: Total Audited Portfolio | C15: =SUM(C11:C14) | D15: =SUM(D11:D14) | E15: =SUM(E11:E14)
B18: PROJECT PORTFOLIO DOCUMENTATION (FOR RECRUITERS & HIRING MANAGERS)
B19: Project Purpose | C19: Demonstrates institutional-grade 3-way automated matching between procurement, accounting, and cash settlement.
B20: Core Technical Skills | C20: 3-Way Reconciliation, Advanced Lookup (INDEX/MATCH, VLOOKUP), Discrepancy Root-Cause Analysis, Financial Controls.
B21: Target Roles | C21: Finance Operations Analyst, Accounts Payable Specialist, Business Operations Analyst, Financial Assurance.
B22: Methodology | C22: Raw vendor invoices are automatically reconciled against AP sub-ledgers and cleared bank statements. Variances exceeding $0.00 trigger automated exception classification and standard audit escalation procedures.

Sheet Reconciliation Engine
A1: Invoice # | B1: Vendor Name | C1: Vendor Billed ($) | D1: AP Ledger Amount ($) | E1: Bank Cleared ($) | F1: Billing vs AP Variance ($) | G1: AP vs Bank Variance ($) | H1: Match Status | I1: Discrepancy Category | J1: Audit Action Required
A2: ='Vendor Invoices (Raw)'!A2 | B2: ='Vendor Invoices (Raw)'!C2 | C2: ='Vendor Invoices (Raw)'!I2 | D2: =IFERROR(VLOOKUP(A2, 'AP Ledger (Raw)'!$A$2:$I$50, 9, FALSE), 0) | E2: =IFERROR(VLOOKUP(A2, 'Bank Statements (Raw)'!$B$2:$D$50, 3, FALSE), 0) | F2: =ROUND(C2-D2, 2) | G2: =ROUND(D2-E2, 2) | H2: =IF(AND(ABS(F2)<0.01, ABS(G2)<0.01, E2>0), "Fully Reconciled", IF(D2=0, "Missing in AP Ledger", IF(E2=0, "Pending Bank Disbursement", "Variance Detected"))) | I2: =IF(H2="Fully Reconciled", "None (Matched)", IF(D2=0, "Unbooked Invoice", IF(E2=0, "Unpaid / In-Transit", IF(ABS(F2)>0.01, "Pricing / Qty Variance", "Bank Settlement Timing")))) | J2: =IF(H2="Fully Reconciled", "No Action Required", IF(H2="Missing in AP Ledger", "Request GRN & PO from Procurement", IF(H2="Pending Bank Disbursement", "Verify Payment Run Batch", "Issue Debit/Credit Note & Dispute")))
A3: ='Vendor Invoices (Raw)'!A3 | B3: ='Vendor Invoices (Raw)'!C3 | C3: ='Vendor Invoices (Raw)'!I3 | D3: =IFERROR(VLOOKUP(A3, 'AP Ledger (Raw)'!$A$2:$I$50, 9, FALSE), 0) | E3: =IFERROR(VLOOKUP(A3, 'Bank Statements (Raw)'!$B$2:$D$50, 3, FALSE), 0) | F3: =ROUND(C3-D3, 2) | G3: =ROUND(D3-E3, 2) | H3: =IF(AND(ABS(F3)<0.01, ABS(G3)<0.01, E3>0), "Fully Reconciled", IF(D3=0, "Missing in AP Ledger", IF(E3=0, "Pending Bank Disbursement", "Variance Detected"))) | I3: =IF(H3="Fully Reconciled", "None (Matched)", IF(D3=0, "Unbooked Invoice", IF(E3=0, "Unpaid / In-Transit", IF(ABS(F3)>0.01, "Pricing / Qty Variance", "Bank Settlement Timing")))) | J3: =IF(H3="Fully Reconciled", "No Action Required", IF(H3="Missing in AP Ledger", "Request GRN & PO from Procurement", IF(H3="Pending Bank Disbursement", "Verify Payment Run Batch", "Issue Debit/Credit Note & Dispute")))
A4: ='Vendor Invoices (Raw)'!A4 | B4: ='Vendor Invoices (Raw)'!C4 | C4: ='Vendor Invoices (Raw)'!I4 | D4: =IFERROR(VLOOKUP(A4, 'AP Ledger (Raw)'!$A$2:$I$50, 9, FALSE), 0) | E4: =IFERROR(VLOOKUP(A4, 'Bank Statements (Raw)'!$B$2:$D$50, 3, FALSE), 0) | F4: =ROUND(C4-D4, 2) | G4: =ROUND(D4-E4, 2) | H4: =IF(AND(ABS(F4)<0.01, ABS(G4)<0.01, E4>0), "Fully Reconciled", IF(D4=0, "Missing in AP Ledger", IF(E4=0, "Pending Bank Disbursement", "Variance Detected"))) | I4: =IF(H4="Fully Reconciled", "None (Matched)", IF(D4=0, "Unbooked Invoice", IF(E4=0, "Unpaid / In-Transit", IF(ABS(F4)>0.01, "Pricing / Qty Variance", "Bank Settlement Timing")))) | J4: =IF(H4="Fully Reconciled", "No Action Required", IF(H4="Missing in AP Ledger", "Request GRN & PO from Procurement", IF(H4="Pending Bank Disbursement", "Verify Payment Run Batch", "Issue Debit/Credit Note & Dispute")))
A5: ='Vendor Invoices (Raw)'!A5 | B5: ='Vendor Invoices (Raw)'!C5 | C5: ='Vendor Invoices (Raw)'!I5 | D5: =IFERROR(VLOOKUP(A5, 'AP Ledger (Raw)'!$A$2:$I$50, 9, FALSE), 0) | E5: =IFERROR(VLOOKUP(A5, 'Bank Statements (Raw)'!$B$2:$D$50, 3, FALSE), 0) | F5: =ROUND(C5-D5, 2) | G5: =ROUND(D5-E5, 2) | H5: =IF(AND(ABS(F5)<0.01, ABS(G5)<0.01, E5>0), "Fully Reconciled", IF(D5=0, "Missing in AP Ledger", IF(E5=0, "Pending Bank Disbursement", "Variance Detected"))) | I5: =IF(H5="Fully Reconciled", "None (Matched)", IF(D5=0, "Unbooked Invoice", IF(E5=0, "Unpaid / In-Transit", IF(ABS(F5)>0.01, "Pricing / Qty Variance", "Bank Settlement Timing")))) | J5: =IF(H5="Fully Reconciled", "No Action Required", IF(H5="Missing in AP Ledger", "Request GRN & PO from Procurement", IF(H5="Pending Bank Disbursement", "Verify Payment Run Batch", "Issue Debit/Credit Note & Dispute")))
A6: ='Vendor Invoices (Raw)'!A6 | B6: ='Vendor Invoices (Raw)'!C6 | C6: ='Vendor Invoices (Raw)'!I6 | D6: =IFERROR(VLOOKUP(A6, 'AP Ledger (Raw)'!$A$2:$I$50, 9, FALSE), 0) | E6: =IFERROR(VLOOKUP(A6, 'Bank Statements (Raw)'!$B$2:$D$50, 3, FALSE), 0) | F6: =ROUND(C6-D6, 2) | G6: =ROUND(D6-E6, 2) | H6: =IF(AND(ABS(F6)<0.01, ABS(G6)<0.01, E6>0), "Fully Reconciled", IF(D6=0, "Missing in AP Ledger", IF(E6=0, "Pending Bank Disbursement", "Variance Detected"))) | I6: =IF(H6="Fully Reconciled", "None (Matched)", IF(D6=0, "Unbooked Invoice", IF(E6=0, "Unpaid / In-Transit", IF(ABS(F6)>0.01, "Pricing / Qty Variance", "Bank Settlement Timing")))) | J6: =IF(H6="Fully Reconciled", "No Action Required", IF(H6="Missing in AP Ledger", "Request GRN & PO from Procurement", IF(H6="Pending Bank Disbursement", "Verify Payment Run Batch", "Issue Debit/Credit Note & Dispute")))
A7: ='Vendor Invoices (Raw)'!A7 | B7: ='Vendor Invoices (Raw)'!C7 | C7: ='Vendor Invoices (Raw)'!I7 | D7: =IFERROR(VLOOKUP(A7, 'AP Ledger (Raw)'!$A$2:$I$50, 9, FALSE), 0) | E7: =IFERROR(VLOOKUP(A7, 'Bank Statements (Raw)'!$B$2:$D$50, 3, FALSE), 0) | F7: =ROUND(C7-D7, 2) | G7: =ROUND(D7-E7, 2) | H7: =IF(AND(ABS(F7)<0.01, ABS(G7)<0.01, E7>0), "Fully Reconciled", IF(D7=0, "Missing in AP Ledger", IF(E7=0, "Pending Bank Disbursement", "Variance Detected"))) | I7: =IF(H7="Fully Reconciled", "None (Matched)", IF(D7=0, "Unbooked Invoice", IF(E7=0, "Unpaid / In-Transit", IF(ABS(F7)>0.01, "Pricing / Qty Variance", "Bank Settlement Timing")))) | J7: =IF(H7="Fully Reconciled", "No Action Required", IF(H7="Missing in AP Ledger", "Request GRN & PO from Procurement", IF(H7="Pending Bank Disbursement", "Verify Payment Run Batch", "Issue Debit/Credit Note & Dispute")))
A8: ='Vendor Invoices (Raw)'!A8 | B8: ='Vendor Invoices (Raw)'!C8 | C8: ='Vendor Invoices (Raw)'!I8 | D8: =IFERROR(VLOOKUP(A8, 'AP Ledger (Raw)'!$A$2:$I$50, 9, FALSE), 0) | E8: =IFERROR(VLOOKUP(A8, 'Bank Statements (Raw)'!$B$2:$D$50, 3, FALSE), 0) | F8: =ROUND(C8-D8, 2) | G8: =ROUND(D8-E8, 2) | H8: =IF(AND(ABS(F8)<0.01, ABS(G8)<0.01, E8>0), "Fully Reconciled", IF(D8=0, "Missing in AP Ledger", IF(E8=0, "Pending Bank Disbursement", "Variance Detected"))) | I8: =IF(H8="Fully Reconciled", "None (Matched)", IF(D8=0, "Unbooked Invoice", IF(E8=0, "Unpaid / In-Transit", IF(ABS(F8)>0.01, "Pricing / Qty Variance", "Bank Settlement Timing")))) | J8: =IF(H8="Fully Reconciled", "No Action Required", IF(H8="Missing in AP Ledger", "Request GRN & PO from Procurement", IF(H8="Pending Bank Disbursement", "Verify Payment Run Batch", "Issue Debit/Credit Note & Dispute")))
A9: ='Vendor Invoices (Raw)'!A9 | B9: ='Vendor Invoices (Raw)'!C9 | C9: ='Vendor Invoices (Raw)'!I9 | D9: =IFERROR(VLOOKUP(A9, 'AP Ledger (Raw)'!$A$2:$I$50, 9, FALSE), 0) | E9: =IFERROR(VLOOKUP(A9, 'Bank Statements (Raw)'!$B$2:$D$50, 3, FALSE), 0) | F9: =ROUND(C9-D9, 2) | G9: =ROUND(D9-E9, 2) | H9: =IF(AND(ABS(F9)<0.01, ABS(G9)<0.01, E9>0), "Fully Reconciled", IF(D9=0, "Missing in AP Ledger", IF(E9=0, "Pending Bank Disbursement", "Variance Detected"))) | I9: =IF(H9="Fully Reconciled", "None (Matched)", IF(D9=0, "Unbooked Invoice", IF(E9=0, "Unpaid / In-Transit", IF(ABS(F9)>0.01, "Pricing / Qty Variance", "Bank Settlement Timing")))) | J9: =IF(H9="Fully Reconciled", "No Action Required", IF(H9="Missing in AP Ledger", "Request GRN & PO from Procurement", IF(H9="Pending Bank Disbursement", "Verify Payment Run Batch", "Issue Debit/Credit Note & Dispute")))
A10: ='Vendor Invoices (Raw)'!A10 | B10: ='Vendor Invoices (Raw)'!C10 | C10: ='Vendor Invoices (Raw)'!I10 | D10: =IFERROR(VLOOKUP(A10, 'AP Ledger (Raw)'!$A$2:$I$50, 9, FALSE), 0) | E10: =IFERROR(VLOOKUP(A10, 'Bank Statements (Raw)'!$B$2:$D$50, 3, FALSE), 0) | F10: =ROUND(C10-D10, 2) | G10: =ROUND(D10-E10, 2) | H10: =IF(AND(ABS(F10)<0.01, ABS(G10)<0.01, E10>0), "Fully Reconciled", IF(D10=0, "Missing in AP Ledger", IF(E10=0, "Pending Bank Disbursement", "Variance Detected"))) | I10: =IF(H10="Fully Reconciled", "None (Matched)", IF(D10=0, "Unbooked Invoice", IF(E10=0, "Unpaid / In-Transit", IF(ABS(F10)>0.01, "Pricing / Qty Variance", "Bank Settlement Timing")))) | J10: =IF(H10="Fully Reconciled", "No Action Required", IF(H10="Missing in AP Ledger", "Request GRN & PO from Procurement", IF(H10="Pending Bank Disbursement", "Verify Payment Run Batch", "Issue Debit/Credit Note & Dispute")))
A11: ='Vendor Invoices (Raw)'!A11 | B11: ='Vendor Invoices (Raw)'!C11 | C11: ='Vendor Invoices (Raw)'!I11 | D11: =IFERROR(VLOOKUP(A11, 'AP Ledger (Raw)'!$A$2:$I$50, 9, FALSE), 0) | E11: =IFERROR(VLOOKUP(A11, 'Bank Statements (Raw)'!$B$2:$D$50, 3, FALSE), 0) | F11: =ROUND(C11-D11, 2) | G11: =ROUND(D11-E11, 2) | H11: =IF(AND(ABS(F11)<0.01, ABS(G11)<0.01, E11>0), "Fully Reconciled", IF(D11=0, "Missing in AP Ledger", IF(E11=0, "Pending Bank Disbursement", "Variance Detected"))) | I11: =IF(H11="Fully Reconciled", "None (Matched)", IF(D11=0, "Unbooked Invoice", IF(E11=0, "Unpaid / In-Transit", IF(ABS(F11)>0.01, "Pricing / Qty Variance", "Bank Settlement Timing")))) | J11: =IF(H11="Fully Reconciled", "No Action Required", IF(H11="Missing in AP Ledger", "Request GRN & PO from Procurement", IF(H11="Pending Bank Disbursement", "Verify Payment Run Batch", "Issue Debit/Credit Note & Dispute")))
A12: ='Vendor Invoices (Raw)'!A12 | B12: ='Vendor Invoices (Raw)'!C12 | C12: ='Vendor Invoices (Raw)'!I12 | D12: =IFERROR(VLOOKUP(A12, 'AP Ledger (Raw)'!$A$2:$I$50, 9, FALSE), 0) | E12: =IFERROR(VLOOKUP(A12, 'Bank Statements (Raw)'!$B$2:$D$50, 3, FALSE), 0) | F12: =ROUND(C12-D12, 2) | G12: =ROUND(D12-E12, 2) | H12: =IF(AND(ABS(F12)<0.01, ABS(G12)<0.01, E12>0), "Fully Reconciled", IF(D12=0, "Missing in AP Ledger", IF(E12=0, "Pending Bank Disbursement", "Variance Detected"))) | I12: =IF(H12="Fully Reconciled", "None (Matched)", IF(D12=0, "Unbooked Invoice", IF(E12=0, "Unpaid / In-Transit", IF(ABS(F12)>0.01, "Pricing / Qty Variance", "Bank Settlement Timing")))) | J12: =IF(H12="Fully Reconciled", "No Action Required", IF(H12="Missing in AP Ledger", "Request GRN & PO from Procurement", IF(H12="Pending Bank Disbursement", "Verify Payment Run Batch", "Issue Debit/Credit Note & Dispute")))
A13: ='Vendor Invoices (Raw)'!A13 | B13: ='Vendor Invoices (Raw)'!C13 | C13: ='Vendor Invoices (Raw)'!I13 | D13: =IFERROR(VLOOKUP(A13, 'AP Ledger (Raw)'!$A$2:$I$50, 9, FALSE), 0) | E13: =IFERROR(VLOOKUP(A13, 'Bank Statements (Raw)'!$B$2:$D$50, 3, FALSE), 0) | F13: =ROUND(C13-D13, 2) | G13: =ROUND(D13-E13, 2) | H13: =IF(AND(ABS(F13)<0.01, ABS(G13)<0.01, E13>0), "Fully Reconciled", IF(D13=0, "Missing in AP Ledger", IF(E13=0, "Pending Bank Disbursement", "Variance Detected"))) | I13: =IF(H13="Fully Reconciled", "None (Matched)", IF(D13=0, "Unbooked Invoice", IF(E13=0, "Unpaid / In-Transit", IF(ABS(F13)>0.01, "Pricing / Qty Variance", "Bank Settlement Timing")))) | J13: =IF(H13="Fully Reconciled", "No Action Required", IF(H13="Missing in AP Ledger", "Request GRN & PO from Procurement", IF(H13="Pending Bank Disbursement", "Verify Payment Run Batch", "Issue Debit/Credit Note & Dispute")))
... A41: ='Vendor Invoices (Raw)'!A41 | B41: ='Vendor Invoices (Raw)'!C41 | C41: ='Vendor Invoices (Raw)'!I41 | D41: =IFERROR(VLOOKUP(A41, 'AP Ledger (Raw)'!$A$2:$I$50, 9, FALSE), 0) | E41: =IFERROR(VLOOKUP(A41, 'Bank Statements (Raw)'!$B$2:$D$50, 3, FALSE), 0) | F41: =ROUND(C41-D41, 2) | G41: =ROUND(D41-E41, 2) | H41: =IF(AND(ABS(F41)<0.01, ABS(G41)<0.01, E41>0), "Fully Reconciled", IF(D41=0, "Missing in AP Ledger", IF(E41=0, "Pending Bank Disbursement", "Variance Detected"))) | I41: =IF(H41="Fully Reconciled", "None (Matched)", IF(D41=0, "Unbooked Invoice", IF(E41=0, "Unpaid / In-Transit", IF(ABS(F41)>0.01, "Pricing / Qty Variance", "Bank Settlement Timing")))) | J41: =IF(H41="Fully Reconciled", "No Action Required", IF(H41="Missing in AP Ledger", "Request GRN & PO from Procurement", IF(H41="Pending Bank Disbursement", "Verify Payment Run Batch", "Issue Debit/Credit Note & Dispute")))

Sheet Vendor Invoices (Raw)
A1: Invoice Number | B1: Vendor ID | C1: Vendor Name | D1: Invoice Date | E1: Billed Qty | F1: Unit Price ($) | G1: Subtotal ($) | H1: Tax Amount (18%) | I1: Total Billed ($)
A2: INV-2026-1001 | B2: VND-1002 | C2: Sterling Tech Solutions | D2: 46266 | E2: 99 | F2: 160.01 | G2: 15840.99 | H2: 2851.38 | I2: 18692.37
A3: INV-2026-1002 | B3: VND-1003 | C3: Beacon Office Supplies | D3: 46289 | E3: 18 | F3: 320.68 | G3: 5772.24 | H3: 1039 | I3: 6811.24
A4: INV-2026-1003 | B4: VND-1007 | C4: Nova Packaging Ltd | D4: 46267 | E4: 8 | F4: 87.48 | G4: 699.84 | H4: 125.97 | I4: 825.81
A5: INV-2026-1004 | B5: VND-1001 | C5: Apex Global Logistics | D5: 46283 | E5: 30 | F5: 336.41 | G5: 10092.3 | H5: 1816.61 | I5: 11908.91
A6: INV-2026-1005 | B6: VND-1004 | C6: Zenith Industrial Parts | D6: 46280 | E6: 80 | F6: 161.28 | G6: 12902.4 | H6: 2322.43 | I6: 15224.83
A7: INV-2026-1006 | B7: VND-1003 | C7: Beacon Office Supplies | D7: 46288 | E7: 59 | F7: 186.1 | G7: 10979.9 | H7: 1976.38 | I7: 12956.28
A8: INV-2026-1007 | B8: VND-1004 | C8: Zenith Industrial Parts | D8: 46296 | E8: 48 | F8: 90.88 | G8: 4362.24 | H8: 785.2 | I8: 5147.44
A9: INV-2026-1008 | B9: VND-1007 | C9: Nova Packaging Ltd | D9: 46269 | E9: 50 | F9: 389 | G9: 19450 | H9: 3501 | I9: 22951
A10: INV-2026-1009 | B10: VND-1001 | C10: Apex Global Logistics | D10: 46289 | E10: 63 | F10: 264.49 | G10: 16662.87 | H10: 2999.32 | I10: 19662.19
A11: INV-2026-1010 | B11: VND-1007 | C11: Nova Packaging Ltd | D11: 46268 | E11: 75 | F11: 167.27 | G11: 12545.25 | H11: 2258.14 | I11: 14803.39
A12: INV-2026-1011 | B12: VND-1006 | C12: Falcon Facility Services | D12: 46284 | E12: 29 | F12: 331.83 | G12: 9623.07 | H12: 1732.15 | I12: 11355.22
A13: INV-2026-1012 | B13: VND-1004 | C13: Zenith Industrial Parts | D13: 46290 | E13: 42 | F13: 444.09 | G13: 18651.78 | H13: 3357.32 | I13: 22009.1
... A41: INV-2026-1040 | B41: VND-1004 | C41: Zenith Industrial Parts | D41: 46284 | E41: 33 | F41: 52.88 | G41: 1745.04 | H41: 314.11 | I41: 2059.15

Sheet AP Ledger (Raw)
A1: Invoice Reference | B1: Vendor ID | C1: Vendor Name | D1: Posting Date | E1: Received Qty | F1: PO Unit Rate ($) | G1: AP Subtotal ($) | H1: AP Tax ($) | I1: Total Approved ($) | J1: Approval Status
A2: INV-2026-1001 | B2: VND-1002 | C2: Sterling Tech Solutions | D2: 46266 | E2: 99 | F2: 160.01 | G2: 15840.99 | H2: 2851.38 | I2: 18692.37 | J2: Approved
A3: INV-2026-1002 | B3: VND-1003 | C3: Beacon Office Supplies | D3: 46289 | E3: 18 | F3: 320.68 | G3: 5772.24 | H3: 1039 | I3: 6811.24 | J3: Approved
A4: INV-2026-1003 | B4: VND-1007 | C4: Nova Packaging Ltd | D4: 46267 | E4: 8 | F4: 87.48 | G4: 699.84 | H4: 125.97 | I4: 825.81 | J4: Approved
A5: INV-2026-1004 | B5: VND-1001 | C5: Apex Global Logistics | D5: 46283 | E5: 30 | F5: 336.41 | G5: 10092.3 | H5: 1816.61 | I5: 11908.91 | J5: Approved
A6: INV-2026-1005 | B6: VND-1004 | C6: Zenith Industrial Parts | D6: 46280 | E6: 80 | F6: 161.28 | G6: 12902.4 | H6: 2322.43 | I6: 15224.83 | J6: Approved
A7: INV-2026-1006 | B7: VND-1003 | C7: Beacon Office Supplies | D7: 46288 | E7: 59 | F7: 186.1 | G7: 10979.9 | H7: 1976.38 | I7: 12956.28 | J7: Approved
A8: INV-2026-1007 | B8: VND-1004 | C8: Zenith Industrial Parts | D8: 46296 | E8: 48 | F8: 86.34 | G8: 4144.32 | H8: 745.98 | I8: 4890.3 | J8: Rate Disputed
A9: INV-2026-1008 | B9: VND-1007 | C9: Nova Packaging Ltd | D9: 46269 | E9: 46 | F9: 389 | G9: 17894 | H9: 3220.92 | I9: 21114.92 | J9: Short-Shipment Logged
A10: INV-2026-1010 | B10: VND-1007 | C10: Nova Packaging Ltd | D10: 46268 | E10: 75 | F10: 167.27 | G10: 12545.25 | H10: 2258.14 | I10: 14803.39 | J10: Pending Clearance
A11: INV-2026-1011 | B11: VND-1006 | C11: Falcon Facility Services | D11: 46284 | E11: 29 | F11: 331.83 | G11: 9623.07 | H11: 1732.15 | I11: 11355.22 | J11: Approved
A12: INV-2026-1012 | B12: VND-1004 | C12: Zenith Industrial Parts | D12: 46290 | E12: 42 | F12: 444.09 | G12: 18651.78 | H12: 3357.32 | I12: 22009.1 | J12: Approved
A13: INV-2026-1013 | B13: VND-1002 | C13: Sterling Tech Solutions | D13: 46278 | E13: 40 | F13: 231.36 | G13: 9254.4 | H13: 1665.79 | I13: 10920.19 | J13: Approved
... A37: INV-2026-1040 | B37: VND-1004 | C37: Zenith Industrial Parts | D37: 46284 | E37: 33 | F37: 52.88 | G37: 1745.04 | H37: 314.11 | I37: 2059.15 | J37: Pending Clearance

Sheet Bank Statements (Raw)
A1: Bank Transaction ID | B1: Invoice Reference | C1: Clearance Date | D1: Disbursed Amount ($) | E1: Bank Status
A2: TXN-BNK-80001 | B2: INV-2026-1001 | C2: 46283 | D2: 18692.37 | E2: Settled
A3: TXN-BNK-80002 | B3: INV-2026-1002 | C3: 46301 | D3: 6811.24 | E3: Settled
A4: TXN-BNK-80003 | B4: INV-2026-1003 | C4: 46284 | D4: 825.81 | E4: Settled
A5: TXN-BNK-80004 | B5: INV-2026-1004 | C5: 46306 | D5: 11908.91 | E5: Settled
A6: TXN-BNK-80005 | B6: INV-2026-1005 | C6: 46290 | D6: 15224.83 | E6: Settled
A7: TXN-BNK-80006 | B7: INV-2026-1006 | C7: 46302 | D7: 12956.28 | E7: Settled
A8: TXN-BNK-80007 | B8: INV-2026-1007 | C8: 46311 | D8: 4890.3 | E8: Partial Settlement
A9: TXN-BNK-80008 | B9: INV-2026-1008 | C9: 46287 | D9: 21114.92 | E9: Under Review
A10: TXN-BNK-80011 | B10: INV-2026-1011 | C10: 46295 | D10: 11355.22 | E10: Settled
A11: TXN-BNK-80012 | B11: INV-2026-1012 | C11: 46307 | D11: 22009.1 | E11: Settled
A12: TXN-BNK-80013 | B12: INV-2026-1013 | C12: 46299 | D12: 10920.19 | E12: Settled
A13: TXN-BNK-80014 | B13: INV-2026-1014 | C13: 46295 | D13: 7894.2 | E13: Settled
... A33: TXN-BNK-80038 | B33: INV-2026-1038 | C33: 46298 | D33: 18502.54 | E33: Under Review
